azure_ad_auth/__init__.py
azure_ad_auth/backends.py
azure_ad_auth/urls.py
azure_ad_auth/utils.py
azure_ad_auth/views.py
django_azure_ad_auth-1.3.1.dist-info/DESCRIPTION.rst
django_azure_ad_auth-1.3.1.dist-info/METADATA
django_azure_ad_auth-1.3.1.dist-info/metadata.json
django_azure_ad_auth-1.3.1.dist-info/RECORD
django_azure_ad_auth-1.3.1.dist-info/top_level.txt
django_azure_ad_auth-1.3.1.dist-info/WHEEL
