Metadata-Version: 2.0
Name: django-azure-ad-auth
Version: 1.3.1
Summary: Authenticated users using Azure Active Directory.
Home-page: https://bitbucket.org/nextscreenlabs/django-azure-ad-auth
Author: Jason Christa
Author-email: jason@zeitcode.com
License: UNKNOWN
Platform: UNKNOWN
Classifier: Environment :: Web Environment
Classifier: License :: OSI Approved :: BSD License
Classifier: Framework :: Django
Classifier: Programming Language :: Python
Requires-Dist: Django (>=1.4)
Requires-Dist: PyJWT (>=1.1.0)
Requires-Dist: cryptography (>=0.9)
Requires-Dist: lxml (>=3.0.0)
Requires-Dist: requests (>=2.0.0)
